README.txt
setup.py
docs/HISTORY.txt
monet/__init__.py
monet.calendar.location.egg-info/PKG-INFO
monet.calendar.location.egg-info/SOURCES.txt
monet.calendar.location.egg-info/dependency_links.txt
monet.calendar.location.egg-info/entry_points.txt
monet.calendar.location.egg-info/namespace_packages.txt
monet.calendar.location.egg-info/not-zip-safe
monet.calendar.location.egg-info/requires.txt
monet.calendar.location.egg-info/top_level.txt
monet/calendar/__init__.py
monet/calendar/location/__init__.py
monet/calendar/location/configure.zcml
monet/calendar/location/exportimport.py
monet/calendar/location/i18n.sh
monet/calendar/location/indexer.py
monet/calendar/location/interfaces.py
monet/calendar/location/searchbarmunicipality.pt
monet/calendar/location/skins.zcml
monet/calendar/location/viewletsmunicipality.py
monet/calendar/location/browser/__init__.py
monet/calendar/location/browser/configure.zcml
monet/calendar/location/browser/event-ui-controls.js
monet/calendar/location/browser/event_view.pt
monet/calendar/location/browser/images/hide_control.gif
monet/calendar/location/browser/images/show_control.gif
monet/calendar/location/browser/stylesheets/monetcalendarlocation.css
monet/calendar/location/locales/monet.calendar.event.pot
monet/calendar/location/locales/monet.calendar.extensions.pot
monet/calendar/location/locales/monet.calendar.location.pot
monet/calendar/location/locales/it/LC_MESSAGES/monet.calendar.event.po
monet/calendar/location/locales/it/LC_MESSAGES/monet.calendar.extensions.po
monet/calendar/location/locales/it/LC_MESSAGES/monet.calendar.location.po
monet/calendar/location/profiles/default/browserlayer.xml
monet/calendar/location/profiles/default/catalog.xml
monet/calendar/location/profiles/default/cssregistry.xml
monet/calendar/location/profiles/default/jsregistry.xml
monet/calendar/location/profiles/default/metadata.xml
monet/calendar/location/profiles/default/monet.calendar.location-various.txt
monet/calendar/location/profiles/default/propertiestool.xml
monet/calendar/location/profiles/default/skins.xml
monet/calendar/location/skins/monet.calendar.location.templates/event_edit.pt
monet/calendar/location/skins/monet.calendar.location.templates/twocolumnsmultiselection.pt