Metadata-Version: 1.0
Name: monet.calendar.location
Version: 0.4.0
Summary: Add Italian features to monet.calendar.event
Home-page: http://plone.org/products/monet.calendar.star
Author: RedTurtle Technology
Author-email: sviluppoplone@redturtle.net
License: GPL
Platform: UNKNOWN
Classifier: Programming Language :: Python
